lsst/alert/stream/__init__.py
lsst/alert/stream/alertConsumer.py
lsst/alert/stream/alertProducer.py
lsst/alert/stream/filterBase.py
lsst/alert/stream/filters.py
lsst/alert/stream/serialization.py
lsst/alert/stream/bin/filterStream.py
lsst/alert/stream/bin/monitorStream.py
lsst/alert/stream/bin/printStream.py
lsst/alert/stream/bin/sendAlertStream.py
lsst_alert_stream-0.3.0.dist-info/LICENSE
lsst_alert_stream-0.3.0.dist-info/METADATA
lsst_alert_stream-0.3.0.dist-info/WHEEL
lsst_alert_stream-0.3.0.dist-info/entry_points.txt
lsst_alert_stream-0.3.0.dist-info/top_level.txt
lsst_alert_stream-0.3.0.dist-info/RECORD
