Metadata-Version: 2.1
Name: lsst-alert-stream
Version: 0.3.0
Summary: Code for interacting with the Vera C. Rubin Observatory alert stream
Home-page: https://github.com/lsst-dm/alert_stream
Author: Spencer Nelson
Author-email: swnelson@uw.edu
License: GPLv3
Platform: UNKNOWN
Classifier: Programming Language :: Python :: 3
Classifier: License :: OSI Approved :: GNU General Public License v3 (GPLv3)
Classifier: Development Status :: 3 - Alpha
Requires-Dist: confluent-kafka
Requires-Dist: fastavro
Requires-Dist: lsst-alert-packet
